setup.py
distributions/Binomialdistribution.py
distributions/Gaussiandistribution.py
distributions/Generaldistribution.py
distributions/__init__.py
intro_distributions.egg-info/PKG-INFO
intro_distributions.egg-info/SOURCES.txt
intro_distributions.egg-info/dependency_links.txt
intro_distributions.egg-info/not-zip-safe
intro_distributions.egg-info/top_level.txt