Metadata-Version: 1.0
Name: intro-distributions
Version: 0.1
Summary: Binomial and Gaussian distribution handling
Home-page: UNKNOWN
Author: UNKNOWN
Author-email: UNKNOWN
License: UNKNOWN
Platform: UNKNOWN
